httpbench/__init__.py
httpbench/apps.py
httpbench/backends.py
httpbench/header.py
httpbench/middlewares.py
httpbench/throttle.py
httpbench/management/__init__.py
httpbench/management/commands/__init__.py
httpbench/management/commands/httpbench.py
httpbench/tests/__init__.py
httpbench/tests/test_header.py
djangohttpbench-0.1.0.dist-info/LICENSE
djangohttpbench-0.1.0.dist-info/METADATA
djangohttpbench-0.1.0.dist-info/WHEEL
djangohttpbench-0.1.0.dist-info/top_level.txt
djangohttpbench-0.1.0.dist-info/RECORD
