Metadata-Version: 2.1
Name: djangohttpbench
Version: 0.1.0
Summary: HTTP load testing tools for Django. Like an apache bench but requests are sent from authenticated users.
Home-page: https://github.com/c-bata/django-httpbench
Author: Masashi Shibata
Author-email: contact@c-bata.link
License: MIT
Platform: UNKNOWN
Requires-Dist: Django
Requires-Dist: requests
